squape/__init__.py
squape/object_tree.py
squape/report.py
squape/settings.py
squape/squishserver.py
squape/video.py
squape/vps.py
squape/internal/__init__.py
squape/internal/exceptions.py
squape/resources/empty_video_with_message.mp4
squape-1.1.dist-info/LICENSE
squape-1.1.dist-info/METADATA
squape-1.1.dist-info/WHEEL
squape-1.1.dist-info/top_level.txt
squape-1.1.dist-info/RECORD
