Metadata-Version: 2.1
Name: squape
Version: 1.1
Summary: Python utilities for the Squish GUI Tester
Author-email: Cyber Alpaca <contact@cyberalpaca.com>
Project-URL: Homepage, https://github.com/CyberAlpaca/squish-api-python-extension
Project-URL: Documentation, https://squape.cyberalpaca.com
Project-URL: Changelog, https://github.com/CyberAlpaca/squish-api-python-extension/blob/main/HISTORY.md
Project-URL: Cyber Alpaca, https://cyberalpaca.com
Classifier: Programming Language :: Python :: 3
Classifier: Programming Language :: Python :: 3.8
Classifier: Programming Language :: Python :: 3.10
Classifier: License :: OSI Approved :: BSD License
Classifier: Operating System :: OS Independent
Requires-Python: >=3.8
License-File: LICENSE
